LeetTerminal/__init__.py
LeetTerminal/main.py
LeetTerminal/scraper.py
LeetTerminal/tools.py
LeetTerminal-1.0.0.dist-info/METADATA
LeetTerminal-1.0.0.dist-info/WHEEL
LeetTerminal-1.0.0.dist-info/entry_points.txt
LeetTerminal-1.0.0.dist-info/top_level.txt
LeetTerminal-1.0.0.dist-info/RECORD
