Metadata-Version: 2.1
Name: LeetTerminal
Version: 1.0.0
Requires-Dist: beautifulsoup4
Requires-Dist: requests
Requires-Dist: rich
Requires-Dist: webdriver-manager
Requires-Dist: selenium
Requires-Dist: cloudscraper
